odoo/addons/shopinvader_payment_sips/README.rst
odoo/addons/shopinvader_payment_sips/__init__.py
odoo/addons/shopinvader_payment_sips/__manifest__.py
odoo/addons/shopinvader_payment_sips/readme/CONTRIBUTORS.rst
odoo/addons/shopinvader_payment_sips/readme/DESCRIPTION.rst
odoo/addons/shopinvader_payment_sips/services/__init__.py
odoo/addons/shopinvader_payment_sips/services/payment_sips.py
odoo/addons/shopinvader_payment_sips/static/description/index.html
odoo12_addon_shopinvader_payment_sips-12.0.2.0.0.dist-info/METADATA
odoo12_addon_shopinvader_payment_sips-12.0.2.0.0.dist-info/WHEEL
odoo12_addon_shopinvader_payment_sips-12.0.2.0.0.dist-info/top_level.txt
odoo12_addon_shopinvader_payment_sips-12.0.2.0.0.dist-info/RECORD
